odoo/addons/website_sale_hide_empty_category/README.rst
odoo/addons/website_sale_hide_empty_category/__init__.py
odoo/addons/website_sale_hide_empty_category/__manifest__.py
odoo/addons/website_sale_hide_empty_category/i18n/website_sale_hide_empty_category.pot
odoo/addons/website_sale_hide_empty_category/models/__init__.py
odoo/addons/website_sale_hide_empty_category/models/product_public_category.py
odoo/addons/website_sale_hide_empty_category/views/website_sale_templates.xml
odoo11_addon_website_sale_hide_empty_category-11.0.1.0.0.dist-info/METADATA
odoo11_addon_website_sale_hide_empty_category-11.0.1.0.0.dist-info/RECORD
odoo11_addon_website_sale_hide_empty_category-11.0.1.0.0.dist-info/WHEEL
odoo11_addon_website_sale_hide_empty_category-11.0.1.0.0.dist-info/top_level.txt
